gradio_molecule2d/__init__.py
gradio_molecule2d/molecule2d.py
gradio_molecule2d/molecule2d.pyi
gradio_molecule2d/templates/component/index.js
gradio_molecule2d/templates/component/style.css
gradio_molecule2d/templates/example/index.js
gradio_molecule2d/templates/example/style.css
gradio_molecule2d-0.0.3.dist-info/METADATA
gradio_molecule2d-0.0.3.dist-info/WHEEL
gradio_molecule2d-0.0.3.dist-info/RECORD
